MANIFEST.in
README.rst
build.py
setup.py
sources/spectral.c
sources/spectral.h
spectral/__init__.py
spectral_aead.egg-info/PKG-INFO
spectral_aead.egg-info/SOURCES.txt
spectral_aead.egg-info/dependency_links.txt
spectral_aead.egg-info/requires.txt
spectral_aead.egg-info/top_level.txt