Metadata-Version: 1.1
Name: spectral-aead
Version: 0.0.4
Summary: An algorithm for authenticated encryption with associated data using Speck and HMAC-SHA256.
Home-page: https://github.com/kpdemetriou/spectral-aead
Author: Phil Demetriou
Author-email: inbox@philonas.net
License: BSD
Platform: UNKNOWN
Classifier: Development Status :: 3 - Alpha
Classifier: Intended Audience :: Developers
Classifier: Intended Audience :: Science/Research
Classifier: Intended Audience :: System Administrators
Classifier: Intended Audience :: Telecommunications Industry
Classifier: License :: OSI Approved :: BSD License
Classifier: Programming Language :: C
Classifier: Programming Language :: Python :: 3
Classifier: Programming Language :: Python :: 3 :: Only
Classifier: Topic :: Security
Classifier: Topic :: Security :: Cryptography
Classifier: Topic :: Utilities
